easy_pay_website/__init__.py
easy_pay_website/core.py
easy_pay_website/py.typed
easy_pay_website-0.8.0.dist-info/METADATA
easy_pay_website-0.8.0.dist-info/WHEEL
easy_pay_website-0.8.0.dist-info/licenses/LICENSE
easy_pay_website-0.8.0.dist-info/RECORD
