Metadata-Version: 2.3
Name: easy_pay_website
Version: 0.8.0
Summary: easy pay website
Project-URL: Documentation, https://asmitul.github.io/easy_pay_website
Project-URL: Issues, https://github.com/asmitul/easy_pay_website/issues
Project-URL: Source, https://github.com/asmitul/easy_pay_website
Author: asmitul
License-Expression: MIT
License-File: LICENSE
Classifier: Development Status :: 4 - Beta
Classifier: Intended Audience :: Developers
Classifier: License :: OSI Approved :: MIT License
Classifier: Programming Language :: Python
Classifier: Programming Language :: Python :: 3.8
Classifier: Programming Language :: Python :: 3.9
Classifier: Programming Language :: Python :: 3.10
Classifier: Programming Language :: Python :: 3.11
Classifier: Programming Language :: Python :: Implementation :: CPython
Classifier: Programming Language :: Python :: Implementation :: PyPy
Classifier: Topic :: Internet
Classifier: Topic :: Software Development
Classifier: Topic :: Software Development :: Libraries
Classifier: Topic :: Software Development :: Libraries :: Application Frameworks
Classifier: Topic :: Software Development :: Libraries :: Python Modules
Requires-Python: <3.12,>=3.8
Requires-Dist: beautifulsoup4>=4.12.2
Requires-Dist: ddddocr==1.4.11
Requires-Dist: odin-functions==0.0.3
Requires-Dist: pillow==9.5.0
Requires-Dist: pytz>=2023.3
Requires-Dist: requests>=2.31.0
Provides-Extra: docs
Requires-Dist: mkdocs-git-revision-date-localized-plugin~=1.1.0; extra == 'docs'
Requires-Dist: mkdocs-material~=8.5.4; extra == 'docs'
Requires-Dist: mkdocstrings[python]~=0.19.0; extra == 'docs'
Requires-Dist: mkdocs~=1.4.0; extra == 'docs'
Provides-Extra: quality
Requires-Dist: black~=22.10.0; extra == 'quality'
Requires-Dist: mypy~=1.4.0; extra == 'quality'
Requires-Dist: pre-commit~=2.20.0; extra == 'quality'
Requires-Dist: ruff~=0.0.263; extra == 'quality'
Provides-Extra: tests
Requires-Dist: pytest-cov~=4.1; extra == 'tests'
Requires-Dist: pytest~=7.1.2; extra == 'tests'
